error404/__init__.py
error404/config.py
error404/results.py
error404/tests.py
error404-1.1.7.dist-info/METADATA
error404-1.1.7.dist-info/RECORD
error404-1.1.7.dist-info/WHEEL
error404-1.1.7.dist-info/top_level.txt
