Metadata-Version: 2.1
Name: error404
Version: 1.1.7
Summary: Colourful tests for Python!
Home-page: https://harens.github.io
Author: harens
Author-email: harensdeveloper@gmail.com
License: GPLv3
Download-URL: https://github.com/harens/error404/archive/master.zip
Project-URL: Source, https://github.com/harens/error404
Project-URL: Tracker, https://github.com/harens/error404/issues
Keywords: tests,emoji
Platform: UNKNOWN
Classifier: Development Status :: 5 - Production/Stable
Classifier: Operating System :: OS Independent
Classifier: Intended Audience :: Developers
Classifier: Intended Audience :: Education
Classifier: License :: OSI Approved :: GNU General Public License v3 (GPLv3)
Classifier: Natural Language :: English
Classifier: Programming Language :: Python :: 3.6
Classifier: Programming Language :: Python :: 3.7
Classifier: Typing :: Typed
